MANIFEST.in
README.rst
setup.py
gamefaqs/__init__.py
gamefaqs/access.py
gamefaqs/game.py
gamefaqs_py.egg-info/PKG-INFO
gamefaqs_py.egg-info/SOURCES.txt
gamefaqs_py.egg-info/dependency_links.txt
gamefaqs_py.egg-info/entry_points.txt
gamefaqs_py.egg-info/pbr.json
gamefaqs_py.egg-info/top_level.txt
scripts/load.py