Metadata-Version: 1.0
Name: gamefaqs-py
Version: 0.1.6
Summary: Retrieve and manage game data from GameFAQS.
Home-page: https://github.com/ryantonini/gamefaqs-py
Author: Ryan Tonini
Author-email: ryantonini@yahoo.com
License: GPLv3
Platform: UNKNOWN
